mt4forexparser/MT4ForexParser.py
mt4forexparser/UniLogger.py
mt4forexparser/__init__.py
mt4forexparser/__main__.py
mt4forexparser-1.1.41.dist-info/LICENSE
mt4forexparser-1.1.41.dist-info/METADATA
mt4forexparser-1.1.41.dist-info/WHEEL
mt4forexparser-1.1.41.dist-info/entry_points.txt
mt4forexparser-1.1.41.dist-info/top_level.txt
mt4forexparser-1.1.41.dist-info/zip-safe
mt4forexparser-1.1.41.dist-info/RECORD
