Metadata-Version: 2.1
Name: mt4forexparser
Version: 1.1.41
Summary: Read forex data in MetaTrader 4 .hst-format and convert into .csv file and pandas dataframe. Also you can draw an interactive chart.
Home-page: https://github.com/Tim55667757/MT4ForexParser/
Author: Timur Gilmullin
Author-email: tim55667757@gmail.com
License: MIT
Download-URL: https://github.com/Tim55667757/MT4ForexParser.git
Keywords: forex,broker,history,csv,stock,trade,candlestick,chart,parser,MetaTrader,MetaTrader4
Platform: UNKNOWN
Classifier: Development Status :: 5 - Production/Stable
Classifier: Environment :: Console
Classifier: Intended Audience :: Financial and Insurance Industry
Classifier: Topic :: Utilities
Classifier: License :: OSI Approved :: MIT License
Classifier: Natural Language :: English
Classifier: Programming Language :: Python :: 3
License-File: LICENSE
Requires-Dist: pandas (>=1.2.2)
Requires-Dist: pricegenerator (>=1.2.46)
